{
  "responses": [
    {
      "labelAnnotations": [
        {
          "mid": "/m/025rgl",
          "description": "plush",
          "score": 0.90923846,
          "topicality": 0.90923846
        },
        {
          "mid": "/m/021mh_",
          "description": "stuffed toy",
          "score": 0.8776991,
          "topicality": 0.8776991
        },
        {
          "mid": "/m/01l0y0",
          "description": "material",
          "score": 0.6509027,
          "topicality": 0.6509027
        },
        {
          "mid": "/m/03gq5hm",
          "description": "font",
          "score": 0.58993185,
          "topicality": 0.58993185
        }
      ],
      "textAnnotations": [
        {
          "locale": "und",
          "description": ".\n宽宽裁吧\n職录像了\n",
          "boundingPoly": {
            "vertices": [
              {
                "x": 127,
                "y": 76
              },
              {
                "x": 323,
                "y": 76
              },
              {
                "x": 323,
                "y": 391
              },
              {
                "x": 127,
                "y": 391
              }
            ]
          }
        },
        {
          "description": ".",
          "boundingPoly": {
            "vertices": [
              {
                "x": 179,
                "y": 78
              },
              {
                "x": 206,
                "y": 76
              },
              {
                "x": 213,
                "y": 171
              },
              {
                "x": 186,
                "y": 173
              }
            ]
          }
        },
        {
          "description": "宽宽裁吧",
          "boundingPoly": {
            "vertices": [
              {
                "x": 127,
                "y": 293
              },
              {
                "x": 307,
                "y": 293
              },
              {
                "x": 307,
                "y": 339
              },
              {
                "x": 127,
                "y": 339
              }
            ]
          }
        },
        {
          "description": "職录像了",
          "boundingPoly": {
            "vertices": [
              {
                "x": 147,
                "y": 338
              },
              {
                "x": 323,
                "y": 338
              },
              {
                "x": 323,
                "y": 391
              },
              {
                "x": 147,
                "y": 391
              }
            ]
          }
        }
      ],
      "fullTextAnnotation": {
        "pages": [
          {
            "width": 400,
            "height": 400,
            "blocks": [
              {
                "boundingBox": {
                  "vertices": [
                    {
                      "x": 179,
                      "y": 78
                    },
                    {
                      "x": 206,
                      "y": 76
                    },
                    {
                      "x": 213,
                      "y": 171
                    },
                    {
                      "x": 186,
                      "y": 173
                    }
                  ]
                },
                "paragraphs": [
                  {
                    "boundingBox": {
                      "vertices": [
                        {
                          "x": 179,
                          "y": 78
                        },
                        {
                          "x": 206,
                          "y": 76
                        },
                        {
                          "x": 213,
                          "y": 171
                        },
                        {
                          "x": 186,
                          "y": 173
                        }
                      ]
                    },
                    "words": [
                      {
                        "boundingBox": {
                          "vertices": [
                            {
                              "x": 179,
                              "y": 78
                            },
                            {
                              "x": 206,
                              "y": 76
                            },
                            {
                              "x": 213,
                              "y": 171
                            },
                            {
                              "x": 186,
                              "y": 173
                            }
                          ]
                        },
                        "symbols": [
                          {
                            "property": {
                              "detectedBreak": {
                                "type": "LINE_BREAK"
                              }
                            },
                            "boundingBox": {
                              "vertices": [
                                {
                                  "x": 179,
                                  "y": 78
                                },
                                {
                                  "x": 206,
                                  "y": 76
                                },
                                {
                                  "x": 213,
                                  "y": 171
                                },
                                {
                                  "x": 186,
                                  "y": 173
                                }
                              ]
                            },
                            "text": ".",
                            "confidence": 0.19
                          }
                        ],
                        "confidence": 0.19
                      }
                    ],
                    "confidence": 0.19
                  }
                ],
                "blockType": "TEXT",
                "confidence": 0.19
              },
              {
                "boundingBox": {
                  "vertices": [
                    {
                      "x": 127,
                      "y": 293
                    },
                    {
                      "x": 323,
                      "y": 293
                    },
                    {
                      "x": 323,
                      "y": 391
                    },
                    {
                      "x": 127,
                      "y": 391
                    }
                  ]
                },
                "paragraphs": [
                  {
                    "boundingBox": {
                      "vertices": [
                        {
                          "x": 127,
                          "y": 293
                        },
                        {
                          "x": 323,
                          "y": 293
                        },
                        {
                          "x": 323,
                          "y": 391
                        },
                        {
                          "x": 127,
                          "y": 391
                        }
                      ]
                    },
                    "words": [
                      {
                        "boundingBox": {
                          "vertices": [
                            {
                              "x": 127,
                              "y": 293
                            },
                            {
                              "x": 307,
                              "y": 293
                            },
                            {
                              "x": 307,
                              "y": 339
                            },
                            {
                              "x": 127,
                              "y": 339
                            }
                          ]
                        },
                        "symbols": [
                          {
                            "boundingBox": {
                              "vertices": [
                                {
                                  "x": 127,
                                  "y": 293
                                },
                                {
                                  "x": 166,
                                  "y": 293
                                },
                                {
                                  "x": 166,
                                  "y": 339
                                },
                                {
                                  "x": 127,
                                  "y": 339
                                }
                              ]
                            },
                            "text": "宽",
                            "confidence": 0.95
                          },
                          {
                            "boundingBox": {
                              "vertices": [
                                {
                                  "x": 174,
                                  "y": 293
                                },
                                {
                                  "x": 213,
                                  "y": 293
                                },
                                {
                                  "x": 213,
                                  "y": 339
                                },
                                {
                                  "x": 174,
                                  "y": 339
                                }
                              ]
                            },
                            "text": "宽",
                            "confidence": 0.94
                          },
                          {
                            "boundingBox": {
                              "vertices": [
                                {
                                  "x": 221,
                                  "y": 293
                                },
                                {
                                  "x": 260,
                                  "y": 293
                                },
                                {
                                  "x": 260,
                                  "y": 339
                                },
                                {
                                  "x": 221,
                                  "y": 339
                                }
                              ]
                            },
                            "text": "裁",
                            "confidence": 0.81
                          },
                          {
                            "property": {
                              "detectedBreak": {
                                "type": "EOL_SURE_SPACE"
                              }
                            },
                            "boundingBox": {
                              "vertices": [
                                {
                                  "x": 268,
                                  "y": 293
                                },
                                {
                                  "x": 307,
                                  "y": 293
                                },
                                {
                                  "x": 307,
                                  "y": 339
                                },
                                {
                                  "x": 268,
                                  "y": 339
                                }
                              ]
                            },
                            "text": "吧",
                            "confidence": 0.6
                          }
                        ],
                        "confidence": 0.82
                      },
                      {
                        "boundingBox": {
                          "vertices": [
                            {
                              "x": 147,
                              "y": 338
                            },
                            {
                              "x": 323,
                              "y": 338
                            },
                            {
                              "x": 323,
                              "y": 391
                            },
                            {
                              "x": 147,
                              "y": 391
                            }
                          ]
                        },
                        "symbols": [
                          {
                            "boundingBox": {
                              "vertices": [
                                {
                                  "x": 147,
                                  "y": 338
                                },
                                {
                                  "x": 183,
                                  "y": 338
                                },
                                {
                                  "x": 183,
                                  "y": 391
                                },
                                {
                                  "x": 147,
                                  "y": 391
                                }
                              ]
                            },
                            "text": "職",
                            "confidence": 0.81
                          },
                          {
                            "boundingBox": {
                              "vertices": [
                                {
                                  "x": 188,
                                  "y": 338
                                },
                                {
                                  "x": 228,
                                  "y": 338
                                },
                                {
                                  "x": 228,
                                  "y": 391
                                },
                                {
                                  "x": 188,
                                  "y": 391
                                }
                              ]
                            },
                            "text": "录",
                            "confidence": 0.04
                          },
                          {
                            "boundingBox": {
                              "vertices": [
                                {
                                  "x": 242,
                                  "y": 338
                                },
                                {
                                  "x": 282,
                                  "y": 338
                                },
                                {
                                  "x": 282,
                                  "y": 391
                                },
                                {
                                  "x": 242,
                                  "y": 391
                                }
                              ]
                            },
                            "text": "像",
                            "confidence": 0.8
                          },
                          {
                            "property": {
                              "detectedBreak": {
                                "type": "LINE_BREAK"
                              }
                            },
                            "boundingBox": {
                              "vertices": [
                                {
                                  "x": 287,
                                  "y": 338
                                },
                                {
                                  "x": 323,
                                  "y": 338
                                },
                                {
                                  "x": 323,
                                  "y": 391
                                },
                                {
                                  "x": 287,
                                  "y": 391
                                }
                              ]
                            },
                            "text": "了",
                            "confidence": 0.55
                          }
                        ],
                        "confidence": 0.55
                      }
                    ],
                    "confidence": 0.68
                  }
                ],
                "blockType": "TEXT",
                "confidence": 0.68
              }
            ]
          }
        ],
        "text": ".\n宽宽裁吧\n職录像了\n"
      },
      "webDetection": {
        "webEntities": [
          {
            "entityId": "/m/072kwm",
            "score": 0.8898,
            "description": "Image macro"
          },
          {
            "entityId": "/m/0h_9v3h",
            "score": 0.56,
            "description": "WeChat"
          },
          {
            "entityId": "/m/02r91d",
            "score": 0.4918,
            "description": "Tencent QQ"
          },
          {
            "entityId": "/g/11c6rh54yr",
            "score": 0.4757,
            "description": "滑稽"
          },
          {
            "entityId": "/m/05m_chm",
            "score": 0.3998,
            "description": "Baidu Tieba"
          },
          {
            "entityId": "/m/017kpc",
            "score": 0.2975,
            "description": "Online chat"
          },
          {
            "entityId": "/m/085n4",
            "score": 0.2964,
            "description": "Website"
          },
          {
            "entityId": "/g/11c2yfjb2q",
            "score": 0.28395,
            "description": "Search Emoji"
          },
          {
            "entityId": "/m/06xw2",
            "score": 0.2366,
            "description": "Search engine"
          },
          {
            "entityId": "/t/2dgg60z74vt0",
            "score": 0.181
          },
          {
            "entityId": "/m/0r4pntj",
            "score": 0.1806,
            "description": "Kumamon"
          },
          {
            "entityId": "/m/0jg24",
            "score": 0.1763,
            "description": "Image"
          },
          {
            "entityId": "/m/04ngjk",
            "score": 0.1744,
            "description": "Middle age"
          },
          {
            "entityId": "/m/0463cq4",
            "score": 0.1639,
            "description": "Crying"
          },
          {
            "entityId": "/m/0gktk54",
            "score": 0.05703,
            "description": "Three Kims"
          }
        ],
        "fullMatchingImages": [
          {
            "url": "https://pic4.zhimg.com/v2-89d8612e888323eb092bb2c62b7cbfc3_b.jpg"
          },
          {
            "url": "https://wx4.sinaimg.cn/large/c36bc670gy1fgcg7qxehxj20b40b43zy.jpg"
          },
          {
            "url": "http://5b0988e595225.cdn.sohucs.com/images/20171111/b9f7b27ceb9943c2a43e579664c9d84f.jpeg"
          }
        ],
        "partialMatchingImages": [
          {
            "url": "https://i1.hoopchina.com.cn/user/116/28440116/28440116-1501589825.jpeg"
          },
          {
            "url": "https://pic4.zhimg.com/v2-abc60f4e08d334c81b4ea4e4494c8d8b_b.jpg"
          },
          {
            "url": "http://wx4.sinaimg.cn/bmiddle/b12045d5gy1fls4v7sqghj20b40b47bp.jpg"
          },
          {
            "url": "https://pic3.zhimg.com/v2-be891801c7ce53ceb0b9ebbf33b58ab6_b.jpg"
          },
          {
            "url": "https://pic4.zhimg.com/80/v2-abc60f4e08d334c81b4ea4e4494c8d8b_hd.jpg"
          },
          {
            "url": "http://www.bkill.com/u/upload/2017/11/22/230124062297.jpg"
          },
          {
            "url": "http://hot.online.sh.cn/images/attachement/jpeg/site1/20180806/IMG90b11c9b88aa48355064867.jpeg"
          },
          {
            "url": "https://pic3.zhimg.com/v2-80b83c23d7a6c3d43b05a4d60d37e186_b.jpg"
          },
          {
            "url": "https://pic4.zhimg.com/v2-df910600592c8d9bd91da8296490d62f_b.jpg"
          },
          {
            "url": "http://inews.gtimg.com/newsapp_match/0/3781182971/0"
          },
          {
            "url": "http://p3.pstatp.com/large/2a3c0004906790c2c466"
          },
          {
            "url": "http://wx4.sinaimg.cn/large/b12045d5gy1fls4v7sqghj20b40b47bp.jpg"
          },
          {
            "url": "http://img.soogif.com/S6WBFMKptUgpM5zonOvcGkH3Fsislg1E.jpeg_jpg"
          },
          {
            "url": "http://p0.ifengimg.com/pmop/2017/1207/EDB3FB15461949D2C2A77D4D33F461B6DC48C4BE_size23_w400_h400.jpeg"
          },
          {
            "url": "http://wx1.sinaimg.cn/bmiddle/ceeb653ely1fpkvvhzkoaj20b40b4weu.jpg"
          },
          {
            "url": "http://image.bee-ji.com/118589"
          },
          {
            "url": "https://pic3.zhimg.com/80/v2-80b83c23d7a6c3d43b05a4d60d37e186_hd.jpg"
          },
          {
            "url": "https://file.digitaling.com/eImg/uimages/20171215/1513330180497479.jpg"
          },
          {
            "url": "http://fwimage.cnfanews.com/weixinimg/2018/20180114/2670237049_29dcee673236f16ae3d1d07cfb995923"
          },
          {
            "url": "https://s1.op46.com/society/20180115104732567400045faf0bbfc3ed.jpg"
          },
          {
            "url": "https://pic2.zhimg.com/v2-2e3f93aa8e2ab0d2f8419a3035f90491_b.jpg"
          },
          {
            "url": "https://pic2.zhimg.com/80/v2-2e3f93aa8e2ab0d2f8419a3035f90491_hd.jpg"
          },
          {
            "url": "https://s1.op46.com/workplace/201801262300225b570001007870c20d21.jpg"
          },
          {
            "url": "https://ainicheng.com/storage/img/4283.jpg"
          },
          {
            "url": "https://static.tigerbbs.com/01c741cf3d855bd849cc62207c523d36?op=imageView2&mode=2&width=256&height=256&format=jpg&quality=100"
          },
          {
            "url": "https://pic3.zhimg.com/v2-53c50b3f5ae66a3aafb9c1adeda60286_b.jpg"
          },
          {
            "url": "https://wx2.sinaimg.cn/thumb150/961e9369ly1flpiro3mxoj20b40b4q4j.jpg"
          },
          {
            "url": "https://pic2.zhimg.com/v2-f3b9890502fbc6586d91b0e93d236166_200x112.jpg"
          },
          {
            "url": "https://pic4.zhimg.com/v2-53c50b3f5ae66a3aafb9c1adeda60286_200x112.jpg"
          },
          {
            "url": "https://i1.kknews.cc/SIG=bfv4km/2p43000110no7qo1r0ps_s.jpg"
          }
        ],
        "pagesWithMatchingImages": [
          {
            "url": "https://www.fabiaoqing.com/search/search/keyword/%E8%8B%8D%E5%A4%A9",
            "pageTitle": "<b>苍天表情包</b>- <b>苍天</b>微信<b>表情包</b>- <b>苍天</b>QQ<b>表情包</b>- 发表情fabiaoqing.com",
            "partialMatchingImages": [
              {
                "url": "http://wx4.sinaimg.cn/bmiddle/b12045d5gy1fls4v7sqghj20b40b47bp.jpg"
              }
            ]
          },
          {
            "url": "https://www.fabiaoqing.com/search/search/keyword/%E8%8B%8D%E5%A4%A9%E7%BB%95%E8%BF%87%E8%B0%81",
            "pageTitle": "<b>苍天</b>绕过谁<b>表情包</b> - 发表情",
            "partialMatchingImages": [
              {
                "url": "http://wx4.sinaimg.cn/bmiddle/b12045d5gy1fls4v7sqghj20b40b47bp.jpg"
              }
            ]
          },
          {
            "url": "https://fabiaoqing.com/tag/detail/id/17182.html",
            "pageTitle": "<b>苍天表情包</b>- <b>苍天</b>微信<b>表情包</b>- <b>苍天</b>qq<b>表情包</b>- 发表情- <b>表情包</b>大全 ...",
            "partialMatchingImages": [
              {
                "url": "http://wx4.sinaimg.cn/bmiddle/b12045d5gy1fls4v7sqghj20b40b47bp.jpg"
              }
            ]
          },
          {
            "url": "https://www.fabiaoqing.com/search/search/keyword/%E8%AE%A9%E8%8B%8D%E5%A4%A9%E7%9F%A5%E9%81%93",
            "pageTitle": "让<b>苍天</b>知道<b>表情包</b> - 发表情",
            "partialMatchingImages": [
              {
                "url": "http://wx1.sinaimg.cn/bmiddle/ceeb653ely1fpkvvhzkoaj20b40b4weu.jpg"
              },
              {
                "url": "http://wx4.sinaimg.cn/bmiddle/b12045d5gy1fls4v7sqghj20b40b47bp.jpg"
              }
            ]
          },
          {
            "url": "http://www.bee-ji.com/detail/161654.html",
            "pageTitle": "让<b>苍天</b>知道我不认输.jpg_的<b>表情包</b>，逗比拯救世界--专业的<b>表情包</b>搜索 ...",
            "partialMatchingImages": [
              {
                "url": "http://image.bee-ji.com/118589"
              }
            ]
          },
          {
            "url": "https://www.fabiaoqing.com/search/search/keyword/%E8%8B%8D%E5%A4%A9%E9%A5%B6%E8%BF%87%E8%B0%81",
            "pageTitle": "<b>苍天</b>饶过谁<b>表情包</b> - 发表情",
            "partialMatchingImages": [
              {
                "url": "http://wx4.sinaimg.cn/bmiddle/b12045d5gy1fls4v7sqghj20b40b47bp.jpg"
              }
            ]
          },
          {
            "url": "https://www.fabiaoqing.com/biaoqing/detail/id/446661.html",
            "pageTitle": "让<b>苍天</b>知道我认输- 你的中年危机已经到达战场_熊本熊_中年危机<b>表情</b> ...",
            "partialMatchingImages": [
              {
                "url": "http://wx4.sinaimg.cn/large/b12045d5gy1fls4v7sqghj20b40b47bp.jpg"
              }
            ]
          },
          {
            "url": "http://www.bee-ji.com/detail/91379.html",
            "pageTitle": "好牛逼的狗杂种啊我认输我认输_的<b>表情包</b>，逗比拯救世界--专业的表情 ...",
            "partialMatchingImages": [
              {
                "url": "http://image.bee-ji.com/118589"
              }
            ]
          },
          {
            "url": "https://www.fabiaoqing.com/search/search/keyword/%E8%AE%A4%E4%B8%8D%E8%AE%A4%E8%BE%93",
            "pageTitle": "认不认输<b>表情包</b> - 发表情",
            "partialMatchingImages": [
              {
                "url": "http://wx1.sinaimg.cn/bmiddle/ceeb653ely1fpkvvhzkoaj20b40b4weu.jpg"
              }
            ]
          },
          {
            "url": "http://www.bee-ji.com/detail/65036.html",
            "pageTitle": "你想让本猪猪认输???放弃吧,骚年_的<b>表情包</b>，逗比拯救世界--专业的 ...",
            "partialMatchingImages": [
              {
                "url": "http://image.bee-ji.com/118589"
              }
            ]
          },
          {
            "url": "https://www.fabiaoqing.com/search/search/keyword/%E6%88%91%E4%B8%8D%E8%AE%A4%E8%BE%93",
            "pageTitle": "我不认输<b>表情包</b> - 发表情",
            "partialMatchingImages": [
              {
                "url": "http://wx1.sinaimg.cn/bmiddle/ceeb653ely1fpkvvhzkoaj20b40b4weu.jpg"
              }
            ]
          },
          {
            "url": "http://www.bkill.com/download/163841.html",
            "pageTitle": "让<b>苍天</b>知道我认输<b>表情包</b>|生活不止眼前的枸杞还有远方的西洋参表情 ...",
            "partialMatchingImages": [
              {
                "url": "http://www.bkill.com/u/upload/2017/11/22/230124062297.jpg"
              }
            ]
          },
          {
            "url": "https://www.fabiaoqing.com/search/search/keyword/%E6%88%91%E8%AE%A4%E8%BE%93",
            "pageTitle": "我认输<b>表情包</b>- 我认输微信<b>表情包</b>- 我认输QQ<b>表情包</b>- 发表情 ...",
            "partialMatchingImages": [
              {
                "url": "http://wx1.sinaimg.cn/bmiddle/ceeb653ely1fpkvvhzkoaj20b40b4weu.jpg"
              },
              {
                "url": "http://wx4.sinaimg.cn/bmiddle/b12045d5gy1fls4v7sqghj20b40b47bp.jpg"
              }
            ]
          },
          {
            "url": "https://fabiaoqing.com/tag/detail/id/20158.html",
            "pageTitle": "认输<b>表情包</b>- 认输微信<b>表情包</b>- 认输qq<b>表情包</b>- 发表情- <b>表情包</b>大全 ...",
            "partialMatchingImages": [
              {
                "url": "http://wx1.sinaimg.cn/bmiddle/ceeb653ely1fpkvvhzkoaj20b40b4weu.jpg"
              },
              {
                "url": "http://wx4.sinaimg.cn/bmiddle/b12045d5gy1fls4v7sqghj20b40b47bp.jpg"
              }
            ]
          },
          {
            "url": "https://www.fabiaoqing.com/search/search/keyword/%E8%AE%A4%E8%BE%93",
            "pageTitle": "认输<b>表情包</b>- 认输微信<b>表情包</b>- 认输QQ<b>表情包</b>- 发表情fabiaoqing.com",
            "partialMatchingImages": [
              {
                "url": "http://wx1.sinaimg.cn/bmiddle/ceeb653ely1fpkvvhzkoaj20b40b4weu.jpg"
              },
              {
                "url": "http://wx4.sinaimg.cn/bmiddle/b12045d5gy1fls4v7sqghj20b40b47bp.jpg"
              }
            ]
          },
          {
            "url": "https://www.fabiaoqing.com/tag/detail/id/1811.html",
            "pageTitle": "知道<b>表情包</b>- 知道微信<b>表情包</b>- 知道qq<b>表情包</b>- 发表情- <b>表情包</b>大全 ...",
            "partialMatchingImages": [
              {
                "url": "http://wx4.sinaimg.cn/bmiddle/b12045d5gy1fls4v7sqghj20b40b47bp.jpg"
              }
            ]
          },
          {
            "url": "https://www.fabiaoqing.com/search/search/keyword/%E8%AE%A4%E8%BE%93%E5%90%A7",
            "pageTitle": "认输吧<b>表情包</b>- 认输吧微信<b>表情包</b>- 认输吧QQ<b>表情包</b>- 发表情 ...",
            "partialMatchingImages": [
              {
                "url": "http://wx1.sinaimg.cn/bmiddle/ceeb653ely1fpkvvhzkoaj20b40b4weu.jpg"
              }
            ]
          },
          {
            "url": "http://www.bee-ji.com/detail/118589.html",
            "pageTitle": "让卷天知道我认输_的<b>表情包</b>，逗比拯救世界--专业的<b>表情包</b>搜索网站",
            "partialMatchingImages": [
              {
                "url": "http://image.bee-ji.com/118589"
              }
            ]
          },
          {
            "url": "https://www.fabiaoqing.com/search/search/keyword/%E7%BB%9D%E4%B8%8D%E8%AE%A4%E8%BE%93",
            "pageTitle": "绝不认输<b>表情包</b> - 发表情",
            "partialMatchingImages": [
              {
                "url": "http://wx1.sinaimg.cn/bmiddle/ceeb653ely1fpkvvhzkoaj20b40b4weu.jpg"
              }
            ]
          },
          {
            "url": "https://www.fabiaoqing.com/search/search/keyword/%E8%AA%8D%E8%BC%B8%E5%90%A7",
            "pageTitle": "認輸吧<b>表情包</b>- 認輸吧微信<b>表情包</b>- 認輸吧QQ<b>表情包</b>- 发表情 ...",
            "partialMatchingImages": [
              {
                "url": "http://wx1.sinaimg.cn/bmiddle/ceeb653ely1fpkvvhzkoaj20b40b4weu.jpg"
              },
              {
                "url": "http://wx4.sinaimg.cn/bmiddle/b12045d5gy1fls4v7sqghj20b40b47bp.jpg"
              }
            ]
          },
          {
            "url": "https://www.fabiaoqing.com/search/search/keyword/%E8%AE%A4%E8%BE%93%E4%BA%86/type/bq/page/1.html",
            "pageTitle": "认输了<b>表情包</b>- 认输了微信<b>表情包</b>- 认输了QQ<b>表情包</b>- 发表情 ...",
            "partialMatchingImages": [
              {
                "url": "http://wx4.sinaimg.cn/bmiddle/b12045d5gy1fls4v7sqghj20b40b47bp.jpg"
              }
            ]
          },
          {
            "url": "https://www.fabiaoqing.com/search/search/keyword/%E4%B8%8D%E8%AA%8D%E8%BC%B8",
            "pageTitle": "不認輸<b>表情包</b>- 不認輸微信<b>表情包</b>- 不認輸QQ<b>表情包</b>- 发表情 ...",
            "partialMatchingImages": [
              {
                "url": "http://wx1.sinaimg.cn/bmiddle/ceeb653ely1fpkvvhzkoaj20b40b4weu.jpg"
              }
            ]
          },
          {
            "url": "https://www.fabiaoqing.com/search/search/keyword/%E4%B8%8D%E8%AE%A4%E8%BE%93",
            "pageTitle": "不认输<b>表情包</b>- 不认输微信<b>表情包</b>- 不认输QQ<b>表情包</b>- 发表情 ...",
            "partialMatchingImages": [
              {
                "url": "http://wx1.sinaimg.cn/bmiddle/ceeb653ely1fpkvvhzkoaj20b40b4weu.jpg"
              }
            ]
          },
          {
            "url": "https://www.fabiaoqing.com/search/search/keyword/%E8%AA%8D%E8%BC%B8",
            "pageTitle": "認輸<b>表情包</b>- 認輸微信<b>表情包</b>- 認輸QQ<b>表情包</b>- 发表情fabiaoqing.com",
            "partialMatchingImages": [
              {
                "url": "http://wx1.sinaimg.cn/bmiddle/ceeb653ely1fpkvvhzkoaj20b40b4weu.jpg"
              },
              {
                "url": "http://wx4.sinaimg.cn/bmiddle/b12045d5gy1fls4v7sqghj20b40b47bp.jpg"
              }
            ]
          },
          {
            "url": "https://www.fabiaoqing.com/search/search/keyword/%E8%AE%A4%E8%BE%93%E4%BA%86%E5%90%97",
            "pageTitle": "认输了吗<b>表情包</b>- 认输了吗微信<b>表情包</b>- 认输了吗QQ<b>表情包</b>- 发表情 ...",
            "partialMatchingImages": [
              {
                "url": "http://wx1.sinaimg.cn/bmiddle/ceeb653ely1fpkvvhzkoaj20b40b4weu.jpg"
              }
            ]
          },
          {
            "url": "http://www.bee-ji.com/detail/103928.html",
            "pageTitle": "等我吃完饭让知道究字怎么写_的<b>表情包</b>，逗比拯救世界--专业的<b>表情包</b> ...",
            "partialMatchingImages": [
              {
                "url": "http://image.bee-ji.com/118589"
              }
            ]
          },
          {
            "url": "http://cj.sina.com.cn/article/detail/1686524201/570701",
            "pageTitle": "广深平均工资又涨了！网友：让<b>苍天</b>知道我认输……__财经头条",
            "partialMatchingImages": [
              {
                "url": "http://n.sinaimg.cn/translate/w381h380/20180114/aBcX-fyqrewh9454487.jpg"
              }
            ]
          },
          {
            "url": "https://fabiaoqing.com/biaoqing/detail/id/567121.html",
            "pageTitle": "群主 - 发<b>表情</b>",
            "partialMatchingImages": [
              {
                "url": "http://wx4.sinaimg.cn/bmiddle/b12045d5gy1fls4v7sqghj20b40b47bp.jpg"
              }
            ]
          },
          {
            "url": "https://www.fabiaoqing.com/biaoqing/detail/id/550655.html",
            "pageTitle": "你的小祖宗硬了_祖宗<b>表情</b>- 发<b>表情</b>- fabiaoqing.com",
            "partialMatchingImages": [
              {
                "url": "http://wx4.sinaimg.cn/bmiddle/b12045d5gy1fls4v7sqghj20b40b47bp.jpg"
              }
            ]
          },
          {
            "url": "https://fabiaoqing.com/search/search/keyword/%E4%B8%AD%E5%B9%B4",
            "pageTitle": "中年<b>表情包</b>- 中年微信<b>表情包</b>- 中年QQ<b>表情包</b>- 发表情fabiaoqing.com",
            "partialMatchingImages": [
              {
                "url": "http://wx4.sinaimg.cn/bmiddle/b12045d5gy1fls4v7sqghj20b40b47bp.jpg"
              }
            ]
          },
          {
            "url": "https://www.fabiaoqing.com/search/search/keyword/%E7%94%9F%E5%8C%96%E5%8D%B1%E6%9C%BA",
            "pageTitle": "生化危机<b>表情包</b>- 生化危机微信<b>表情包</b>- 生化危机QQ<b>表情包</b>- 发表情 ...",
            "partialMatchingImages": [
              {
                "url": "http://wx4.sinaimg.cn/bmiddle/b12045d5gy1fls4v7sqghj20b40b47bp.jpg"
              }
            ]
          },
          {
            "url": "https://www.fabiaoqing.com/search/search/keyword/%E4%B8%AD%E5%B9%B4%E4%BA%BA%E8%A1%A8%E6%83%85",
            "pageTitle": "中年人表情<b>表情包</b> - 发表情",
            "partialMatchingImages": [
              {
                "url": "http://wx4.sinaimg.cn/bmiddle/b12045d5gy1fls4v7sqghj20b40b47bp.jpg"
              }
            ]
          },
          {
            "url": "https://www.fabiaoqing.com/search/search/keyword/%E9%92%B1%E5%BE%88%E5%BF%AB%E5%88%B0%E8%BE%BE",
            "pageTitle": "钱很快到达<b>表情包</b> - 发表情",
            "partialMatchingImages": [
              {
                "url": "http://wx4.sinaimg.cn/bmiddle/b12045d5gy1fls4v7sqghj20b40b47bp.jpg"
              }
            ]
          },
          {
            "url": "https://www.fabiaoqing.com/tag/detail/id/57.html",
            "pageTitle": "熊本熊<b>表情包</b>- 熊本熊微信<b>表情包</b>- 熊本熊qq<b>表情包</b>- 发表情- <b>表情包</b> ...",
            "partialMatchingImages": [
              {
                "url": "http://wx4.sinaimg.cn/bmiddle/b12045d5gy1fls4v7sqghj20b40b47bp.jpg"
              }
            ]
          },
          {
            "url": "https://www.weibo.com/ttarticle/p/show?id=2310474150212707938481",
            "pageTitle": "小仙女斗图<b>表情包</b>（史上最全版） - WEIBO",
            "fullMatchingImages": [
              {
                "url": "https://wx4.sinaimg.cn/large/c36bc670gy1fgcg7qxehxj20b40b43zy.jpg"
              }
            ]
          },
          {
            "url": "https://www.weibo.com/ttarticle/p/show?id=2310474144714071865708",
            "pageTitle": "仙女<b>表情包</b>（史上最全版） - WEIBO",
            "fullMatchingImages": [
              {
                "url": "https://wx4.sinaimg.cn/large/c36bc670gy1fgcg7qxehxj20b40b43zy.jpg"
              }
            ]
          },
          {
            "url": "http://www.bee-ji.com/detail/15743.html",
            "pageTitle": "你卷婆说你性无能_的<b>表情包</b>，逗比拯救世界--专业的<b>表情包</b>搜索网站",
            "partialMatchingImages": [
              {
                "url": "http://image.bee-ji.com/118589"
              }
            ]
          },
          {
            "url": "http://www.bee-ji.com/detail/43757.html",
            "pageTitle": "耳朵卷在绳子上_的<b>表情包</b>，逗比拯救世界--专业的<b>表情包</b>搜索网站",
            "partialMatchingImages": [
              {
                "url": "http://image.bee-ji.com/118589"
              }
            ]
          },
          {
            "url": "http://www.bee-ji.com/detail/94243.html",
            "pageTitle": "如果让我知道你按了添加到表情那你死定了_的<b>表情包</b>，逗比拯救世界 ...",
            "partialMatchingImages": [
              {
                "url": "http://image.bee-ji.com/118589"
              }
            ]
          },
          {
            "url": "http://news.sun0769.com/photo/dg/201801/t20180115_7711876_7.shtml",
            "pageTitle": "扎心！广深平均工资又涨了！网友：让<b>苍天</b>知道我认输……_新闻频道_ ...",
            "partialMatchingImages": [
              {
                "url": "http://news.sun0769.com/photo/dg/201801/W020180115319897370774.jpg"
              }
            ]
          },
          {
            "url": "http://www.bee-ji.com/detail/139106.html",
            "pageTitle": "读书破万卷.装逼如有神_的<b>表情包</b>，逗比拯救世界--专业的<b>表情包</b>搜索 ...",
            "partialMatchingImages": [
              {
                "url": "http://image.bee-ji.com/118589"
              }
            ]
          },
          {
            "url": "http://www.bee-ji.com/detail/5974.html",
            "pageTitle": "吓得我赶紧卷了个大白兔奶糖_的<b>表情包</b>，逗比拯救世界--专业的<b>表情包</b> ...",
            "partialMatchingImages": [
              {
                "url": "http://image.bee-ji.com/118589"
              }
            ]
          },
          {
            "url": "http://kuaibao.qq.com/s/20180621A0TV6400?refer=spider",
            "pageTitle": "熊本熊<b>表情包</b>合集-天天快报",
            "partialMatchingImages": [
              {
                "url": "http://inews.gtimg.com/newsapp_match/0/3781182971/0"
              }
            ]
          },
          {
            "url": "http://www.bee-ji.com/detail/13839.html",
            "pageTitle": "我会让你知道自己有几斤几两_的<b>表情包</b>，逗比拯救世界--专业的<b>表情包</b> ...",
            "partialMatchingImages": [
              {
                "url": "http://image.bee-ji.com/118589"
              }
            ]
          },
          {
            "url": "https://www.weibo.com/ttarticle/p/show?id=2310474231864830265561",
            "pageTitle": "小仙女<b>表情包</b>合集（史上最全版） - WEIBO",
            "fullMatchingImages": [
              {
                "url": "https://wx4.sinaimg.cn/large/c36bc670gy1fgcg7qxehxj20b40b43zy.jpg"
              }
            ]
          },
          {
            "url": "https://www.weibo.com/ttarticle/p/show?id=2310474231864830265561&mod=zwenzhang?comment=1",
            "pageTitle": "小仙女<b>表情包</b>合集（史上最全版） - WEIBO",
            "fullMatchingImages": [
              {
                "url": "https://wx4.sinaimg.cn/large/c36bc670gy1fgcg7qxehxj20b40b43zy.jpg"
              }
            ]
          },
          {
            "url": "http://k.sina.com.cn/article_2286101382_88432386019001ys0.html",
            "pageTitle": "扎心！广深平均工资又涨了！网友：让<b>苍天</b>知道我认输…… - 手机新浪网",
            "partialMatchingImages": [
              {
                "url": "http://n.sinaimg.cn/translate/w381h380/20180114/aBcX-fyqrewh9454487.jpg"
              }
            ]
          },
          {
            "url": "https://www.weibo.com/ttarticle/p/show?id=2310474144714071865708&luicode=20000061&lfid=4144714074876457",
            "pageTitle": "仙女<b>表情包</b>（史上最全版） - WEIBO",
            "fullMatchingImages": [
              {
                "url": "https://wx4.sinaimg.cn/large/c36bc670gy1fgcg7qxehxj20b40b43zy.jpg"
              }
            ]
          },
          {
            "url": "http://www.twoeggz.com/news/2583451.html",
            "pageTitle": "熊本熊<b>表情包</b>50张：你成功引起我的注意_新闻_蛋蛋赞",
            "partialMatchingImages": [
              {
                "url": "http://p3.pstatp.com/large/2a3c0004906790c2c466"
              }
            ]
          },
          {
            "url": "https://kknews.cc/entertainment/vp4g9la.html",
            "pageTitle": "撩妹<b>表情包</b>41（熊本熊<b>表情包</b>） - 每日頭條",
            "partialMatchingImages": [
              {
                "url": "https://i1.kknews.cc/SIG=bfv4km/2p43000110no7qo1r0ps_s.jpg"
              }
            ]
          },
          {
            "url": "https://kknews.cc/news/vm5k6o2.html",
            "pageTitle": "熊本熊<b>表情包</b>大全- 每日頭條",
            "partialMatchingImages": [
              {
                "url": "https://i1.kknews.cc/SIG=bfv4km/2p43000110no7qo1r0ps_s.jpg"
              }
            ]
          },
          {
            "url": "http://www.sohu.com/a/203758176_803168",
            "pageTitle": "<b>表情包</b>丨双11要零花钱<b>表情包</b>~ ​​​​_搜狐搞笑_搜狐网",
            "fullMatchingImages": [
              {
                "url": "http://5b0988e595225.cdn.sohucs.com/images/20171111/8d80e16c1234439d8020b6b4e0e4b087.jpeg"
              }
            ]
          },
          {
            "url": "https://kknews.cc/news/g2vjj28.html",
            "pageTitle": "熊本熊<b>表情包</b>- 每日頭條",
            "partialMatchingImages": [
              {
                "url": "https://i1.kknews.cc/SIG=bfv4km/2p43000110no7qo1r0ps_s.jpg"
              }
            ]
          },
          {
            "url": "https://fabiaoqing.com/biaoqing/detail/id/281851.html",
            "pageTitle": "算我求你了- 小仙女们应该有的觉悟_熊本熊_小仙女_萌萌哒<b>表情</b>- 发 ...",
            "fullMatchingImages": [
              {
                "url": "http://wx4.sinaimg.cn/large/c36bc670gy1fgcg7qxehxj20b40b43zy.jpg"
              }
            ]
          },
          {
            "url": "https://kknews.cc/news/gvjog9m.html",
            "pageTitle": "熊本熊<b>表情包</b>：情侶互懟的日常- 每日頭條",
            "partialMatchingImages": [
              {
                "url": "https://i1.kknews.cc/SIG=bfv4km/2p43000110no7qo1r0ps_s.jpg"
              }
            ]
          },
          {
            "url": "https://www.fabiaoqing.com/biaoqing/detail/id/541030.html",
            "pageTitle": "让卷天知道我认输_天知道_认输<b>表情</b>- 发<b>表情</b>- fabiaoqing.com",
            "partialMatchingImages": [
              {
                "url": "http://wx1.sinaimg.cn/large/ceeb653ely1fpkvvhzkoaj20b40b4weu.jpg"
              }
            ]
          },
          {
            "url": "https://kknews.cc/news/kvr6pr.html",
            "pageTitle": "熊本熊污系列<b>表情包</b>，能不能再污一點，太逗了！ - 每日頭條",
            "partialMatchingImages": [
              {
                "url": "https://i1.kknews.cc/SIG=bfv4km/2p43000110no7qo1r0ps_s.jpg"
              }
            ]
          },
          {
            "url": "https://www.1995t.com/photo/101667.html",
            "pageTitle": "让卷天知道我认输-<b>表情包</b>图片-斗图党",
            "partialMatchingImages": [
              {
                "url": "https://ws3.sinaimg.cn/large/9150e4e5ly1fpqt731obuj20b40b4weu.jpg"
              }
            ]
          },
          {
            "url": "https://kknews.cc/zh-sg/entertainment/vp4g9la.html",
            "pageTitle": "撩妹<b>表情包</b>41（熊本熊<b>表情包</b>） - 每日头条 - 每日頭條",
            "partialMatchingImages": [
              {
                "url": "https://i1.kknews.cc/SIG=bfv4km/2p43000110no7qo1r0ps_s.jpg"
              }
            ]
          },
          {
            "url": "https://kknews.cc/news/46j56v3.html",
            "pageTitle": "日本進口熊本熊<b>表情包</b>- 每日頭條",
            "partialMatchingImages": [
              {
                "url": "https://i1.kknews.cc/SIG=bfv4km/2p43000110no7qo1r0ps_s.jpg"
              }
            ]
          },
          {
            "url": "https://kknews.cc/news/vamx2z2.html",
            "pageTitle": "母親節給媽媽發的熊本<b>表情包</b>~親愛的女神快收下吧- 每日頭條",
            "partialMatchingImages": [
              {
                "url": "https://i1.kknews.cc/SIG=bfv4km/2p43000110no7qo1r0ps_s.jpg"
              }
            ]
          },
          {
            "url": "https://kknews.cc/entertainment/x5pg5bg.html",
            "pageTitle": "分享一組灰常經典的熊本熊<b>表情包</b>！ - 每日頭條",
            "partialMatchingImages": [
              {
                "url": "https://i1.kknews.cc/SIG=bfv4km/2p43000110no7qo1r0ps_s.jpg"
              }
            ]
          },
          {
            "url": "https://www.laohu8.com/post/227242",
            "pageTitle": "$Facebook(FB)$这股要全民博反弹，万一再死一遍呢？ - 老虎社区",
            "partialMatchingImages": [
              {
                "url": "https://static.tigerbbs.com/01c741cf3d855bd849cc62207c523d36?op=imageView2&mode=2&width=256&height=256&format=jpg&quality=100"
              }
            ]
          },
          {
            "url": "http://www.soogif.com/phone/search/%E5%A4%84%E5%AF%B9%E8%B1%A1",
            "pageTitle": "处对象GIF动态图_处对象<b>表情包</b>_处对象GIF动图-SOOGIF",
            "partialMatchingImages": [
              {
                "url": "http://img.soogif.com/S6WBFMKptUgpM5zonOvcGkH3Fsislg1E.jpeg_jpg"
              }
            ]
          },
          {
            "url": "http://www.sohu.com/a/203722221_661909",
            "pageTitle": "<b>表情包</b>丨双11要零花钱<b>表情包</b>~ ​​​​_搜狐搞笑_搜狐网",
            "fullMatchingImages": [
              {
                "url": "http://5b0988e595225.cdn.sohucs.com/images/20171111/b9f7b27ceb9943c2a43e579664c9d84f.jpeg"
              }
            ]
          },
          {
            "url": "https://www.doutula.com/photo/list?page=305",
            "pageTitle": "斗图<b>表情包</b> - 最新斗图表情- 斗图<b>表情包</b>- 金馆长表情库- 真正的斗图 ...",
            "partialMatchingImages": [
              {
                "url": "https://ws3.sinaimg.cn/bmiddle/9150e4e5ly1fpqt731obuj20b40b4weu.jpg"
              }
            ]
          },
          {
            "url": "https://www.doutula.com/photo/7093226",
            "pageTitle": "让卷天知道我认输- 斗图<b>表情包</b>- 金馆长表情库- 真正的斗图网站 ...",
            "partialMatchingImages": [
              {
                "url": "https://ws3.sinaimg.cn/large/9150e4e5ly1fpqt731obuj20b40b4weu.jpg"
              }
            ]
          },
          {
            "url": "https://www.laohu8.com/post/230910",
            "pageTitle": "$小米集团-W(01810)$有多少人憋着抄底呢？  举手… - 老虎社区",
            "partialMatchingImages": [
              {
                "url": "https://static.tigerbbs.com/01c741cf3d855bd849cc62207c523d36?op=imageView2&mode=2&width=256&height=256&format=jpg&quality=100"
              }
            ]
          },
          {
            "url": "https://ainicheng.com/xiongbenxiongbiaoqingbao?page=3",
            "pageTitle": "熊本熊<b>表情包</b>-",
            "partialMatchingImages": [
              {
                "url": "https://ainicheng.com/storage/img/4283.jpg"
              }
            ]
          },
          {
            "url": "https://kknews.cc/zh-my/fashion/ogb529p.html",
            "pageTitle": "熊本熊系列<b>表情包</b>都说死猪不怕开水烫越到开学心越浪- 每日头条",
            "partialMatchingImages": [
              {
                "url": "https://i1.kknews.cc/SIG=bfv4km/2p43000110no7qo1r0ps_s.jpg"
              }
            ]
          },
          {
            "url": "https://ainicheng.com/article/1025",
            "pageTitle": "熊本熊<b>表情包</b>：你的中年危机到啦-爱你城",
            "partialMatchingImages": [
              {
                "url": "https://ainicheng.com/storage/img/4283.jpg"
              }
            ]
          },
          {
            "url": "https://www.laohu8.com/post/229568",
            "pageTitle": "$小米集团-W(01810)$我想问一下，买外汇寄出去买股票。那我到时候 ...",
            "partialMatchingImages": [
              {
                "url": "https://static.tigerbbs.com/01c741cf3d855bd849cc62207c523d36?op=imageView2&mode=2&width=256&height=256&format=jpg&quality=100"
              }
            ]
          },
          {
            "url": "http://www.soogif.com/phone/search/%E4%BB%96%E4%BB%AC%E4%B8%8D%E8%BF%87%E6%98%AF%E6%83%B3%E9%AA%82%E6%88%91%E4%BA%86",
            "pageTitle": "他们不过是想骂我了<b>表情包</b>-SOOGIF",
            "partialMatchingImages": [
              {
                "url": "http://img.soogif.com/S6WBFMKptUgpM5zonOvcGkH3Fsislg1E.jpeg_jpg"
              }
            ]
          },
          {
            "url": "https://www.digitaling.com/articles/42150.html",
            "pageTitle": "「佛系90后」围剿注意力，却逃不出自带宿命感的“中年标签” - 数英",
            "partialMatchingImages": [
              {
                "url": "https://file.digitaling.com/eImg/uimages/20171215/1513330180497479.jpg"
              }
            ]
          },
          {
            "url": "http://www.soogif.com/phone/search/1/%E5%BC%80%E9%99%A4%E9%99%88%E6%B8%85%E6%B3%89%E5%85%9A%E7%B1%8D",
            "pageTitle": "开除陈清泉党籍<b>表情包</b>-SOOGIF",
            "partialMatchingImages": [
              {
                "url": "http://img.soogif.com/S6WBFMKptUgpM5zonOvcGkH3Fsislg1E.jpeg_jpg"
              }
            ]
          },
          {
            "url": "https://ainicheng.com/user/15?page=4",
            "pageTitle": "是糯米米呀ฅ -爱你城",
            "partialMatchingImages": [
              {
                "url": "https://ainicheng.com/storage/img/4283.jpg"
              }
            ]
          },
          {
            "url": "http://www.soogif.com/phone/search/2/%E7%9F%A5%E9%81%93%E7%9C%9F%E7%9B%B8%E7%9A%84%E6%88%91",
            "pageTitle": "知道真相的我<b>表情包</b>-SOOGIF",
            "partialMatchingImages": [
              {
                "url": "http://img.soogif.com/S6WBFMKptUgpM5zonOvcGkH3Fsislg1E.jpeg_jpg"
              }
            ]
          },
          {
            "url": "http://soogif.com/phone/search/2/%E5%BC%80%E9%99%A4%E9%99%88%E6%B8%85%E6%B3%89%E5%85%9A%E7%B1%8D",
            "pageTitle": "开除陈清泉党籍<b>表情包</b>-SOOGIF",
            "partialMatchingImages": [
              {
                "url": "http://img.soogif.com/S6WBFMKptUgpM5zonOvcGkH3Fsislg1E.jpeg_jpg"
              }
            ]
          },
          {
            "url": "https://www.laohu8.com/post/229959",
            "pageTitle": "$小米集团-W(01810)$今天大盘也不好，，没事。看看隔壁家印客总 ...",
            "partialMatchingImages": [
              {
                "url": "https://static.tigerbbs.com/01c741cf3d855bd849cc62207c523d36?op=imageView2&mode=2&width=256&height=256&format=jpg&quality=100"
              }
            ]
          },
          {
            "url": "https://www.laohu8.com/post/230887",
            "pageTitle": "$小米集团-W(01810)$天天都是先砸盘，然后尾盘偷袭拉升。但我就是 ...",
            "partialMatchingImages": [
              {
                "url": "https://static.tigerbbs.com/01c741cf3d855bd849cc62207c523d36?op=imageView2&mode=2&width=256&height=256&format=jpg&quality=100"
              }
            ]
          },
          {
            "url": "https://www.laohu8.com/post/230777",
            "pageTitle": "$小米集团-W(01810)$今天小米要涨，我get到了- 老虎社区",
            "partialMatchingImages": [
              {
                "url": "https://static.tigerbbs.com/01c741cf3d855bd849cc62207c523d36?op=imageView2&mode=2&width=256&height=256&format=jpg&quality=100"
              }
            ]
          },
          {
            "url": "http://www.soogif.com/phone/search/2/%E4%BD%A0%E8%BF%99%E6%98%AF%E5%92%8C%E5%A4%A7%E5%93%A5%E8%AF%B4%E8%AF%9D%E7%9A%84%E6%80%81%E5%BA%A6%E5%90%97",
            "pageTitle": "你这是和大哥说话的态度吗<b>表情包</b>-SOOGIF",
            "partialMatchingImages": [
              {
                "url": "http://img.soogif.com/S6WBFMKptUgpM5zonOvcGkH3Fsislg1E.jpeg_jpg"
              }
            ]
          },
          {
            "url": "http://www.soogif.com/phone/search/2/%E5%8E%9F%E6%9D%A5%E6%98%AF%E5%88%B0%E4%BA%86%E5%96%9D%E4%B8%8B%E5%8D%88%E8%8C%B6%E7%9A%84%E6%97%B6%E9%97%B4%E4%BA%86",
            "pageTitle": "原来是到了喝下午茶的时间了<b>表情包</b>-SOOGIF",
            "partialMatchingImages": [
              {
                "url": "http://img.soogif.com/S6WBFMKptUgpM5zonOvcGkH3Fsislg1E.jpeg_jpg"
              }
            ]
          },
          {
            "url": "https://www.laohu8.com/post/230084",
            "pageTitle": "小米集团-W(01810) - 老虎社区-美股",
            "partialMatchingImages": [
              {
                "url": "https://static.tigerbbs.com/01c741cf3d855bd849cc62207c523d36?op=imageView2&mode=2&width=256&height=256&format=jpg&quality=100"
              }
            ]
          },
          {
            "url": "https://www.laohu8.com/post/230544",
            "pageTitle": "$好未来(TAL)$有点意思，第一个波段做空成功，按理应该还有几次 ...",
            "partialMatchingImages": [
              {
                "url": "https://static.tigerbbs.com/01c741cf3d855bd849cc62207c523d36?op=imageView2&mode=2&width=256&height=256&format=jpg&quality=100"
              }
            ]
          },
          {
            "url": "https://www.laohu8.com/post/232846",
            "pageTitle": "$好未来(TAL)$空两手试试- 老虎社区",
            "partialMatchingImages": [
              {
                "url": "https://static.tigerbbs.com/01c741cf3d855bd849cc62207c523d36?op=imageView2&mode=2&width=256&height=256&format=jpg&quality=100"
              }
            ]
          },
          {
            "url": "https://www.laohu8.com/post/213759",
            "pageTitle": "没错，6.15号发帖开三倍杠杆做空的就是我。 - 老虎社区",
            "partialMatchingImages": [
              {
                "url": "https://static.tigerbbs.com/01c741cf3d855bd849cc62207c523d36?op=imageView2&mode=2&width=256&height=256&format=jpg&quality=100"
              }
            ]
          },
          {
            "url": "https://www.laohu8.com/post/221178",
            "pageTitle": "$小米集团-W(01810)$被控制了，22上不了了，肯定回调了，同志们先 ...",
            "partialMatchingImages": [
              {
                "url": "https://static.tigerbbs.com/01c741cf3d855bd849cc62207c523d36?op=imageView2&mode=2&width=256&height=256&format=jpg&quality=100"
              }
            ]
          },
          {
            "url": "https://ainicheng.com/search?q=%E4%BD%A0&page=129",
            "pageTitle": "搜索- 爱你城",
            "partialMatchingImages": [
              {
                "url": "https://ainicheng.com/storage/img/4283.jpg"
              }
            ]
          },
          {
            "url": "https://www.laohu8.com/post/223201",
            "pageTitle": "$小米集团-W(01810)$不断加仓，被小米来回收割，不能瞎几把倒腾了 ...",
            "partialMatchingImages": [
              {
                "url": "https://static.tigerbbs.com/01c741cf3d855bd849cc62207c523d36?op=imageView2&mode=2&width=256&height=256&format=jpg&quality=100"
              }
            ]
          },
          {
            "url": "https://www.laohu8.com/m/post/238289",
            "pageTitle": "迪士尼(DIS)$$SnapInc(SNAP)$都是双杀，厉害了。。。 - 老虎社区",
            "partialMatchingImages": [
              {
                "url": "https://static.tigerbbs.com/01c741cf3d855bd849cc62207c523d36?op=imageView2&mode=2&width=256&height=256&format=jpg&quality=100"
              }
            ]
          },
          {
            "url": "https://www.zanyiba.com/qqbiaoqing/203399_20.html",
            "pageTitle": "小仙女图片<b>表情包</b>带字(20)-赞一把 - 搞笑图片",
            "fullMatchingImages": [
              {
                "url": "https://wx4.sinaimg.cn/large/c36bc670gy1fgcg7qxehxj20b40b43zy.jpg"
              }
            ]
          },
          {
            "url": "https://www.weibo.com/u/1877335631",
            "pageTitle": "主播口罩卡的微博_微博 - WEIBO",
            "partialMatchingImages": [
              {
                "url": "https://wx2.sinaimg.cn/thumb150/961e9369ly1flpiro3mxoj20b40b4q4j.jpg"
              }
            ]
          },
          {
            "url": "https://www.zhihu.com/question/268450915/answer/340561130",
            "pageTitle": "有哪些让你惊艳到的名字？ - 知乎",
            "partialMatchingImages": [
              {
                "url": "https://pic4.zhimg.com/v2-df910600592c8d9bd91da8296490d62f_b.jpg"
              }
            ]
          },
          {
            "url": "https://www.zhihu.com/question/280853476/answer/420849277",
            "pageTitle": "如何评价京东618 各种提前涨价和虚假折扣？ - 知乎",
            "partialMatchingImages": [
              {
                "url": "https://pic2.zhimg.com/80/v2-2e3f93aa8e2ab0d2f8419a3035f90491_hd.jpg"
              },
              {
                "url": "https://pic2.zhimg.com/v2-2e3f93aa8e2ab0d2f8419a3035f90491_b.jpg"
              }
            ]
          },
          {
            "url": "https://www.zhihu.com/question/280853476/answer/418541403",
            "pageTitle": "如何评价京东618 各种提前涨价和虚假折扣？ - 知乎",
            "partialMatchingImages": [
              {
                "url": "https://pic2.zhimg.com/80/v2-2e3f93aa8e2ab0d2f8419a3035f90491_hd.jpg"
              },
              {
                "url": "https://pic2.zhimg.com/v2-2e3f93aa8e2ab0d2f8419a3035f90491_b.jpg"
              }
            ]
          },
          {
            "url": "https://www.zhihu.com/question/280853476/answer/422401471",
            "pageTitle": "如何评价京东618 各种提前涨价和虚假折扣？ - 知乎",
            "partialMatchingImages": [
              {
                "url": "https://pic2.zhimg.com/80/v2-2e3f93aa8e2ab0d2f8419a3035f90491_hd.jpg"
              },
              {
                "url": "https://pic2.zhimg.com/v2-2e3f93aa8e2ab0d2f8419a3035f90491_b.jpg"
              }
            ]
          },
          {
            "url": "https://www.zhihu.com/question/280853476/answer/417345755",
            "pageTitle": "如何评价京东618各种提前涨价和虚假折扣？ - 知乎",
            "partialMatchingImages": [
              {
                "url": "https://pic4.zhimg.com/80/v2-2e3f93aa8e2ab0d2f8419a3035f90491_hd.jpg"
              }
            ]
          },
          {
            "url": "https://www.zhihu.com/question/61733083",
            "pageTitle": "澎湃“美数课”板块中的数据可视化效果是通过什么软件/工具实现的 ...",
            "partialMatchingImages": [
              {
                "url": "https://pic4.zhimg.com/v2-53c50b3f5ae66a3aafb9c1adeda60286_200x112.jpg"
              },
              {
                "url": "https://pic3.zhimg.com/v2-53c50b3f5ae66a3aafb9c1adeda60286_b.jpg"
              }
            ]
          },
          {
            "url": "https://www.zhihu.com/question/268450915",
            "pageTitle": "有哪些让你惊艳到的名字？ - 知乎",
            "partialMatchingImages": [
              {
                "url": "https://pic4.zhimg.com/v2-df910600592c8d9bd91da8296490d62f_b.jpg"
              }
            ]
          }
        ],
        "visuallySimilarImages": [
          {
            "url": "http://wx1.sinaimg.cn/bmiddle/ceeb653ely1fpkvvhzkoaj20b40b4weu.jpg"
          },
          {
            "url": "http://www.yutudou.com/uploads/allimg/180310/1-1P3101G332.jpg"
          },
          {
            "url": "http://www.yutudou.com/uploads/allimg/180310/1-1P3101G332-50.jpg"
          },
          {
            "url": "http://5b0988e595225.cdn.sohucs.com/images/20180703/7ca59812bec342a7af27720f5a8e632f.jpeg"
          },
          {
            "url": "http://www.yutudou.com/uploads/allimg/180310/1-1P3101G333.jpg"
          },
          {
            "url": "http://media.lutouwang.net/news_img//20180731/f7/54b29b62b58d94fd8a4bc960d8a2a4f7"
          },
          {
            "url": "http://4.pic.9ht.com/up/2016-6/2016617141316.jpg"
          },
          {
            "url": "https://ws2.sinaimg.cn/large/9150e4e5ly1fjlunosmwqj20qo0qcac2.jpg"
          },
          {
            "url": "http://pic.962.net/up/2017-8/15018990872347165.jpg"
          },
          {
            "url": "https://www.liciwang.com/upload/i04.pic.sogou.com/414a44ed88b0bb46.jpg"
          }
        ],
        "bestGuessLabels": [
          {
            "label": "苍天 啊 表情 包",
            "languageCode": "zh-CN"
          }
        ]
      }
    }
  ]
}